{
  "IcoMoonType": "selection",
  "icons": [
    {
      "icon": {
        "paths": [
          "M731.429 530.286v-274.286c0-20-16.571-36.571-36.571-36.571h-274.286c-14.857 0-28 9.143-33.714 22.286-5.714 13.714-2.857 29.714 8 40l82.286 82.286-305.143 305.143c-14.286 14.286-14.286 37.143 0 51.429l58.286 58.286c14.286 14.286 37.143 14.286 51.429 0l305.143-305.143 82.286 82.286c6.857 7.429 16 10.857 25.714 10.857 4.571 0 9.714-1.143 14.286-2.857 13.143-5.714 22.286-18.857 22.286-33.714zM877.714 237.714v548.571c0 90.857-73.714 164.571-164.571 164.571h-548.571c-90.857 0-164.571-73.714-164.571-164.571v-548.571c0-90.857 73.714-164.571 164.571-164.571h548.571c90.857 0 164.571 73.714 164.571 164.571z"
        ],
        "attrs": [
          {}
        ],
        "width": 878,
        "isMulticolor": false,
        "isMulticolor2": false,
        "tags": [
          "external-link-square"
        ],
        "grid": 14
      },
      "attrs": [
        {}
      ],
      "properties": {
        "order": 1,
        "id": 0,
        "prevSize": 20,
        "name": "external-link-square"
      },
      "setIdx": 0,
      "setId": 4,
      "iconIdx": 0
    },
    {
      "icon": {
        "paths": [
          "M716.8 102.4v870.4l-204.8-204.8-204.8 204.8v-870.4c0-28.314 29.952-52.224 51.2-51.2h307.2c35.277-1.024 51.2 22.886 51.2 51.2z"
        ],
        "attrs": [],
        "isMulticolor": false,
        "isMulticolor2": false,
        "tags": [
          "bookmark"
        ],
        "grid": 20
      },
      "attrs": [],
      "properties": {
        "id": 32,
        "order": 65,
        "prevSize": 20,
        "name": "bookmark"
      },
      "setIdx": 2,
      "setId": 2,
      "iconIdx": 31
    },
    {
      "icon": {
        "paths": [
          "M231.219 386.458c22.323-22.835 53.402-24.627 80.691 0l200.090 191.846 200.090-191.846c27.29-24.627 58.419-22.835 80.589 0 22.323 22.784 20.89 61.286 0 82.688-20.787 21.402-240.384 230.502-240.384 230.502-11.11 11.418-25.702 17.152-40.294 17.152s-29.184-5.734-40.397-17.152c0 0-219.494-209.101-240.384-230.502-20.941-21.402-22.323-59.904 0-82.688z"
        ],
        "attrs": [],
        "isMulticolor": false,
        "isMulticolor2": false,
        "tags": [
          "chevron-down"
        ],
        "grid": 20
      },
      "attrs": [],
      "properties": {
        "id": 34,
        "order": 56,
        "prevSize": 20,
        "name": "chevron-down"
      },
      "setIdx": 2,
      "setId": 2,
      "iconIdx": 33
    },
    {
      "icon": {
        "paths": [
          "M637.542 231.219c22.835 22.323 24.627 53.402 0 80.691l-191.846 200.090 191.846 200.090c24.627 27.29 22.835 58.419 0 80.589-22.784 22.323-61.286 20.89-82.688 0-21.402-20.787-230.502-240.384-230.502-240.384-11.418-11.11-17.152-25.702-17.152-40.294s5.734-29.184 17.152-40.397c0 0 209.101-219.494 230.502-240.384 21.402-20.941 59.904-22.323 82.688 0z"
        ],
        "attrs": [],
        "isMulticolor": false,
        "isMulticolor2": false,
        "tags": [
          "chevron-left"
        ],
        "grid": 20
      },
      "attrs": [],
      "properties": {
        "id": 35,
        "order": 55,
        "prevSize": 20,
        "name": "chevron-left"
      },
      "setIdx": 2,
      "setId": 2,
      "iconIdx": 34
    },
    {
      "icon": {
        "paths": [
          "M469.146 231.219c21.402 20.89 230.502 240.384 230.502 240.384 11.418 11.213 17.152 25.805 17.152 40.397s-5.734 29.184-17.152 40.294c0 0-209.101 219.597-230.502 240.384-21.402 20.89-59.904 22.323-82.688 0-22.835-22.221-24.627-53.299 0-80.589l191.846-200.090-191.846-200.090c-24.627-27.29-22.835-58.419 0-80.691 22.784-22.323 61.286-20.941 82.688 0z"
        ],
        "attrs": [],
        "isMulticolor": false,
        "isMulticolor2": false,
        "tags": [
          "chevron-right"
        ],
        "grid": 20
      },
      "attrs": [],
      "properties": {
        "id": 36,
        "order": 54,
        "prevSize": 20,
        "name": "chevron-right"
      },
      "setIdx": 2,
      "setId": 2,
      "iconIdx": 35
    },
    {
      "icon": {
        "paths": [
          "M687.002 402.381c13.875-13.722 36.301-13.722 50.074 0 13.824 13.722 13.926 35.891 0 49.613l-200.090 196.096c-13.824 13.722-36.198 13.722-50.125 0l-200.090-196.096c-13.824-13.67-13.824-35.891 0-49.613 13.875-13.722 36.301-13.722 50.074 0l175.155 160.819 175.002-160.819z"
        ],
        "attrs": [],
        "isMulticolor": false,
        "isMulticolor2": false,
        "tags": [
          "chevron-small-down"
        ],
        "grid": 20
      },
      "attrs": [],
      "properties": {
        "id": 37,
        "order": 53,
        "prevSize": 20,
        "name": "chevron-small-down"
      },
      "setIdx": 2,
      "setId": 2,
      "iconIdx": 36
    },
    {
      "icon": {
        "paths": [
          "M621.619 687.002c13.722 13.875 13.722 36.301 0 50.074-13.722 13.824-35.891 13.926-49.613 0l-196.096-200.090c-13.722-13.824-13.722-36.198 0-50.125l196.096-200.090c13.67-13.824 35.891-13.824 49.613 0 13.722 13.875 13.722 36.301 0 50.074l-160.819 175.155 160.819 175.002z"
        ],
        "attrs": [],
        "isMulticolor": false,
        "isMulticolor2": false,
        "tags": [
          "chevron-small-left"
        ],
        "grid": 20
      },
      "attrs": [],
      "properties": {
        "id": 38,
        "order": 52,
        "prevSize": 20,
        "name": "chevron-small-left"
      },
      "setIdx": 2,
      "setId": 2,
      "iconIdx": 37
    },
    {
      "icon": {
        "paths": [
          "M563.2 512l-160.819-175.104c-13.722-13.824-13.722-36.198 0-50.074 13.722-13.824 35.891-13.824 49.613 0l196.096 200.090c13.722 13.875 13.722 36.301 0 50.125l-196.096 200.090c-13.67 13.926-35.891 13.824-49.613 0-13.722-13.773-13.722-36.198 0-50.074l160.819-175.053z"
        ],
        "attrs": [],
        "isMulticolor": false,
        "isMulticolor2": false,
        "tags": [
          "chevron-small-right"
        ],
        "grid": 20
      },
      "attrs": [],
      "properties": {
        "id": 39,
        "order": 51,
        "prevSize": 20,
        "name": "chevron-small-right"
      },
      "setIdx": 2,
      "setId": 2,
      "iconIdx": 38
    },
    {
      "icon": {
        "paths": [
          "M336.998 621.619c-13.875 13.722-36.301 13.722-50.074 0s-13.926-35.891 0-49.613l200.090-196.096c13.824-13.722 36.198-13.722 50.125 0l200.090 196.096c13.824 13.67 13.824 35.891 0 49.613-13.875 13.722-36.301 13.722-50.125 0l-175.104-160.819-175.002 160.819z"
        ],
        "attrs": [],
        "isMulticolor": false,
        "isMulticolor2": false,
        "tags": [
          "chevron-small-up"
        ],
        "grid": 20
      },
      "attrs": [],
      "properties": {
        "id": 40,
        "order": 50,
        "prevSize": 20,
        "name": "chevron-small-up"
      },
      "setIdx": 2,
      "setId": 2,
      "iconIdx": 39
    },
    {
      "icon": {
        "paths": [
          "M891.802 312.781c13.926-13.722 36.301-13.722 50.125 0s13.875 35.891 0 49.613l-404.89 400.896c-13.824 13.722-36.198 13.722-50.125 0l-404.89-400.896c-13.824-13.722-13.824-35.891 0-49.613 13.875-13.722 36.301-13.722 50.125 0l379.853 365.619 379.802-365.619z"
        ],
        "attrs": [],
        "isMulticolor": false,
        "isMulticolor2": false,
        "tags": [
          "chevron-thin-down"
        ],
        "grid": 20
      },
      "attrs": [],
      "properties": {
        "id": 41,
        "order": 49,
        "prevSize": 20,
        "name": "chevron-thin-down"
      },
      "setIdx": 2,
      "setId": 2,
      "iconIdx": 40
    },
    {
      "icon": {
        "paths": [
          "M711.219 891.802c13.722 13.926 13.722 36.301 0 50.125s-35.891 13.875-49.613 0l-400.896-404.89c-13.722-13.824-13.722-36.198 0-50.125l400.896-404.89c13.722-13.824 35.891-13.824 49.613 0 13.722 13.875 13.722 36.301 0 50.125l-365.619 379.853 365.619 379.802z"
        ],
        "attrs": [],
        "isMulticolor": false,
        "isMulticolor2": false,
        "tags": [
          "chevron-thin-left"
        ],
        "grid": 20
      },
      "attrs": [],
      "properties": {
        "id": 42,
        "order": 43,
        "prevSize": 20,
        "name": "chevron-thin-left"
      },
      "setIdx": 2,
      "setId": 2,
      "iconIdx": 41
    },
    {
      "icon": {
        "paths": [
          "M678.4 512l-365.619-379.904c-13.722-13.824-13.722-36.198 0-50.125 13.722-13.824 35.891-13.824 49.613 0l400.896 404.89c13.722 13.875 13.722 36.301 0 50.125l-400.896 404.89c-13.722 13.875-35.891 13.824-49.613 0-13.722-13.773-13.722-36.198 0-50.125l365.619-379.75z"
        ],
        "attrs": [],
        "isMulticolor": false,
        "isMulticolor2": false,
        "tags": [
          "chevron-thin-right"
        ],
        "grid": 20
      },
      "attrs": [],
      "properties": {
        "id": 43,
        "order": 42,
        "prevSize": 20,
        "name": "chevron-thin-right"
      },
      "setIdx": 2,
      "setId": 2,
      "iconIdx": 42
    },
    {
      "icon": {
        "paths": [
          "M132.198 711.219c-13.926 13.722-36.301 13.722-50.125 0s-13.875-35.891 0-49.613l404.89-400.896c13.824-13.722 36.198-13.722 50.125 0l404.89 400.896c13.824 13.722 13.824 35.891 0 49.613-13.875 13.722-36.301 13.722-50.074 0l-379.904-365.619-379.802 365.619z"
        ],
        "attrs": [],
        "isMulticolor": false,
        "isMulticolor2": false,
        "tags": [
          "chevron-thin-up"
        ],
        "grid": 20
      },
      "attrs": [],
      "properties": {
        "id": 44,
        "order": 47,
        "prevSize": 20,
        "name": "chevron-thin-up"
      },
      "setIdx": 2,
      "setId": 2,
      "iconIdx": 43
    },
    {
      "icon": {
        "paths": [
          "M792.781 637.542c-22.323 22.835-53.402 24.627-80.691 0l-200.090-191.846-200.090 191.846c-27.29 24.627-58.419 22.835-80.589 0-22.323-22.784-20.89-61.286 0-82.688 20.787-21.402 240.384-230.502 240.384-230.502 11.11-11.418 25.702-17.152 40.294-17.152s29.184 5.734 40.397 17.152c0 0 219.494 209.101 240.384 230.502 20.941 21.402 22.323 59.904 0 82.688z"
        ],
        "attrs": [],
        "isMulticolor": false,
        "isMulticolor2": false,
        "tags": [
          "chevron-up"
        ],
        "grid": 20
      },
      "attrs": [],
      "properties": {
        "id": 45,
        "order": 48,
        "prevSize": 20,
        "name": "chevron-up"
      },
      "setIdx": 2,
      "setId": 2,
      "iconIdx": 44
    },
    {
      "icon": {
        "paths": [
          "M640.256 445.338l-128.256 117.862-128.307-117.862c-10.138-10.035-26.522-10.035-36.762 0-10.086 10.035-10.086 26.368 0 36.352l146.637 143.718c10.189 10.035 26.624 10.035 36.71 0l146.637-143.718c10.189-9.984 10.138-26.317 0-36.352-10.086-10.035-26.47-10.035-36.659 0zM512 20.48c-271.462 0-491.52 220.058-491.52 491.52 0 271.514 220.058 491.52 491.52 491.52s491.52-220.006 491.52-491.52c0-271.462-220.058-491.52-491.52-491.52zM512 939.725c-236.288 0-427.725-191.488-427.725-427.725s191.437-427.725 427.725-427.725c236.186 0 427.725 191.488 427.725 427.725s-191.539 427.725-427.725 427.725z"
        ],
        "attrs": [],
        "isMulticolor": false,
        "isMulticolor2": false,
        "tags": [
          "chevron-with-circle-down"
        ],
        "grid": 20
      },
      "attrs": [],
      "properties": {
        "id": 46,
        "order": 46,
        "prevSize": 20,
        "name": "chevron-with-circle-down"
      },
      "setIdx": 2,
      "setId": 2,
      "iconIdx": 45
    },
    {
      "icon": {
        "paths": [
          "M578.662 346.931c-10.035-10.086-26.368-10.086-36.352 0l-143.718 146.688c-10.035 10.189-10.035 26.624 0 36.71l143.718 146.637c9.984 10.189 26.317 10.138 36.352 0 10.035-10.086 10.035-26.522 0-36.71l-117.862-128.256 117.862-128.307c10.035-10.138 10.035-26.522 0-36.762zM512 20.48c-271.462 0-491.52 220.058-491.52 491.52 0 271.514 220.058 491.52 491.52 491.52s491.52-220.006 491.52-491.52c0-271.462-220.058-491.52-491.52-491.52zM512 939.725c-236.288 0-427.725-191.488-427.725-427.725s191.437-427.725 427.725-427.725c236.186 0 427.725 191.488 427.725 427.725s-191.539 427.725-427.725 427.725z"
        ],
        "attrs": [],
        "isMulticolor": false,
        "isMulticolor2": false,
        "tags": [
          "chevron-with-circle-left"
        ],
        "grid": 20
      },
      "attrs": [],
      "properties": {
        "id": 47,
        "order": 45,
        "prevSize": 20,
        "name": "chevron-with-circle-left"
      },
      "setIdx": 2,
      "setId": 2,
      "iconIdx": 46
    },
    {
      "icon": {
        "paths": [
          "M563.2 512l-117.862-128.307c-10.035-10.138-10.035-26.573 0-36.762 10.035-10.086 26.368-10.086 36.352 0l143.718 146.637c10.035 10.189 10.035 26.624 0 36.71l-143.718 146.637c-9.984 10.189-26.317 10.138-36.352 0-10.035-10.086-10.035-26.522 0-36.71l117.862-128.205zM512 20.48c271.462 0 491.52 220.058 491.52 491.52 0 271.514-220.058 491.52-491.52 491.52s-491.52-220.006-491.52-491.52c0-271.462 220.058-491.52 491.52-491.52zM512 939.725c236.186 0 427.725-191.488 427.725-427.725s-191.539-427.725-427.725-427.725c-236.288 0-427.725 191.488-427.725 427.725-0.051 236.237 191.437 427.725 427.725 427.725z"
        ],
        "attrs": [],
        "isMulticolor": false,
        "isMulticolor2": false,
        "tags": [
          "chevron-with-circle-right"
        ],
        "grid": 20
      },
      "attrs": [],
      "properties": {
        "id": 48,
        "order": 44,
        "prevSize": 20,
        "name": "chevron-with-circle-right"
      },
      "setIdx": 2,
      "setId": 2,
      "iconIdx": 47
    },
    {
      "icon": {
        "paths": [
          "M530.381 398.592c-10.189-10.035-26.624-10.035-36.71 0l-146.637 143.718c-10.189 9.984-10.138 26.317 0 36.352 10.086 10.035 26.522 10.035 36.71 0l128.256-117.862 128.307 117.862c10.138 10.035 26.522 10.035 36.762 0 10.086-10.035 10.086-26.368 0-36.352l-146.688-143.718zM512 20.48c-271.462 0-491.52 220.058-491.52 491.52 0 271.514 220.058 491.52 491.52 491.52s491.52-220.006 491.52-491.52c0-271.462-220.058-491.52-491.52-491.52zM512 939.725c-236.288 0-427.725-191.488-427.725-427.725s191.437-427.725 427.725-427.725c236.186 0 427.725 191.488 427.725 427.725s-191.539 427.725-427.725 427.725z"
        ],
        "attrs": [],
        "isMulticolor": false,
        "isMulticolor2": false,
        "tags": [
          "chevron-with-circle-up"
        ],
        "grid": 20
      },
      "attrs": [],
      "properties": {
        "id": 49,
        "order": 57,
        "prevSize": 20,
        "name": "chevron-with-circle-up"
      },
      "setIdx": 2,
      "setId": 2,
      "iconIdx": 48
    },
    {
      "icon": {
        "paths": [
          "M512.051 399.36c-62.208 0-112.691 50.432-112.691 112.64s50.483 112.64 112.691 112.64c62.208 0 112.589-50.432 112.589-112.64s-50.381-112.64-112.589-112.64zM512.051 266.24c62.208 0 112.589-50.483 112.589-112.64s-50.381-112.64-112.589-112.64c-62.208 0-112.691 50.432-112.691 112.64s50.483 112.64 112.691 112.64zM512.051 757.76c-62.208 0-112.691 50.432-112.691 112.64s50.483 112.64 112.691 112.64c62.208 0 112.589-50.432 112.589-112.64s-50.381-112.64-112.589-112.64z"
        ],
        "attrs": [],
        "isMulticolor": false,
        "isMulticolor2": false,
        "tags": [
          "dots-three-vertical"
        ],
        "grid": 20
      },
      "attrs": [],
      "properties": {
        "id": 61,
        "order": 58,
        "prevSize": 20,
        "name": "dots-three-vertical"
      },
      "setIdx": 2,
      "setId": 2,
      "iconIdx": 60
    },
    {
      "icon": {
        "paths": [
          "M921.6 102.4h-819.2c-56.32 0-102.4 46.080-102.4 102.4v614.4c0 56.32 46.080 102.4 102.4 102.4h819.2c56.32 0 102.4-46.080 102.4-102.4v-614.4c0-56.32-46.080-102.4-102.4-102.4zM230.4 192c21.197 0 38.4 17.203 38.4 38.4s-17.203 38.4-38.4 38.4c-21.197 0-38.4-17.203-38.4-38.4s17.203-38.4 38.4-38.4zM89.6 230.4c0-21.197 17.203-38.4 38.4-38.4s38.4 17.203 38.4 38.4c0 21.197-17.203 38.4-38.4 38.4s-38.4-17.203-38.4-38.4zM921.6 819.2h-819.2v-460.8h819.2v460.8zM921.6 256h-614.4v-51.2h615.373l-0.973 51.2z"
        ],
        "attrs": [],
        "isMulticolor": false,
        "isMulticolor2": false,
        "tags": [
          "browser"
        ],
        "grid": 20
      },
      "attrs": [],
      "properties": {
        "id": 117,
        "order": 66,
        "prevSize": 20,
        "name": "browser"
      },
      "setIdx": 2,
      "setId": 2,
      "iconIdx": 116
    },
    {
      "icon": {
        "paths": [
          "M292.813 755.2c-12.083 0-24.269-4.25-33.997-12.902l-259.072-230.298 273.459-243.098c21.094-18.688 53.453-16.896 72.243 4.25s16.896 53.504-4.25 72.294l-187.341 166.554 172.954 153.702c21.146 18.79 23.040 51.149 4.25 72.294-10.086 11.418-24.166 17.203-38.246 17.203zM750.797 755.098l273.459-243.098-259.072-230.298c-21.146-18.79-53.504-16.896-72.243 4.25-18.79 21.146-16.896 53.504 4.25 72.294l172.954 153.754-187.341 166.502c-21.146 18.79-23.040 51.149-4.25 72.294 10.086 11.418 24.166 17.203 38.246 17.203 12.083 0 24.269-4.25 33.997-12.902zM511.283 827.648l102.4-614.4c4.659-27.904-14.182-54.272-42.086-58.931-28.006-4.71-54.323 14.182-58.88 42.086l-102.4 614.4c-4.659 27.904 14.182 54.272 42.086 58.931 2.867 0.461 5.632 0.666 8.448 0.666 24.576 0 46.285-17.766 50.432-42.752z"
        ],
        "attrs": [],
        "isMulticolor": false,
        "isMulticolor2": false,
        "tags": [
          "code"
        ],
        "grid": 20
      },
      "attrs": [],
      "properties": {
        "id": 135,
        "order": 67,
        "prevSize": 20,
        "name": "code"
      },
      "setIdx": 2,
      "setId": 2,
      "iconIdx": 134
    },
    {
      "icon": {
        "paths": [
          "M952.32 204.8h-880.64c-39.475 0-71.68 32.205-71.68 71.68v471.040c0 39.373 32.205 71.68 71.629 71.68h880.64c39.424 0 71.68-32.307 71.68-71.68v-471.040c0.051-39.475-32.256-71.68-71.629-71.68zM563.2 307.2h102.4v102.4h-102.4v-102.4zM716.8 460.8v102.4h-102.4v-102.4h102.4zM409.6 307.2h102.4v102.4h-102.4v-102.4zM563.2 460.8v102.4h-102.4v-102.4h102.4zM256 307.2h102.4v102.4h-102.4v-102.4zM409.6 460.8v102.4h-102.4v-102.4h102.4zM102.4 307.2h102.4v102.4h-102.4v-102.4zM256 460.8v102.4h-102.4v-102.4h102.4zM204.8 716.8h-102.4v-102.4h102.4v102.4zM768 716.8h-512v-102.4h512v102.4zM921.6 716.8h-102.4v-102.4h102.4v102.4zM768 563.2v-102.4h102.4v102.4h-102.4zM921.6 409.6h-204.8v-102.4h204.8v102.4z"
        ],
        "attrs": [],
        "isMulticolor": false,
        "isMulticolor2": false,
        "tags": [
          "keyboard"
        ],
        "grid": 20
      },
      "attrs": [],
      "properties": {
        "id": 195,
        "order": 75,
        "prevSize": 20,
        "name": "keyboard"
      },
      "setIdx": 2,
      "setId": 2,
      "iconIdx": 194
    },
    {
      "icon": {
        "paths": [
          "M1011.405 800.307c-12.646-18.995-89.805-134.707-89.805-134.707v-460.8c0-56.422-46.080-102.4-102.4-102.4h-614.4c-56.371 0-102.4 45.978-102.4 102.4v460.8c0 0-77.158 115.712-89.805 134.707-12.595 18.893-12.595 29.798-12.595 44.493v25.6c0 25.6 25.6 51.2 51.149 51.2h921.702c25.549 0 51.149-25.6 51.149-51.2v-25.6c0-14.694 0-25.6-12.595-44.493zM358.4 819.2l30.72-51.2h245.76l30.72 51.2h-307.2zM819.2 614.4h-614.4v-409.6h614.4v409.6z"
        ],
        "attrs": [],
        "isMulticolor": false,
        "isMulticolor2": false,
        "tags": [
          "laptop"
        ],
        "grid": 20
      },
      "attrs": [],
      "properties": {
        "id": 199,
        "order": 74,
        "prevSize": 20,
        "name": "laptop"
      },
      "setIdx": 2,
      "setId": 2,
      "iconIdx": 198
    },
    {
      "icon": {
        "paths": [
          "M839.68 460.8h-655.36c-28.262 0-30.72 22.886-30.72 51.2s2.458 51.2 30.72 51.2h655.36c28.262 0 30.72-22.886 30.72-51.2s-2.458-51.2-30.72-51.2zM839.68 665.6h-655.36c-28.262 0-30.72 22.886-30.72 51.2s2.458 51.2 30.72 51.2h655.36c28.262 0 30.72-22.886 30.72-51.2s-2.458-51.2-30.72-51.2zM184.32 358.4h655.36c28.262 0 30.72-22.886 30.72-51.2s-2.458-51.2-30.72-51.2h-655.36c-28.262 0-30.72 22.886-30.72 51.2s2.458 51.2 30.72 51.2z"
        ],
        "attrs": [],
        "isMulticolor": false,
        "isMulticolor2": false,
        "tags": [
          "menu"
        ],
        "grid": 20
      },
      "attrs": [],
      "properties": {
        "id": 225,
        "order": 63,
        "prevSize": 20,
        "name": "menu"
      },
      "setIdx": 2,
      "setId": 2,
      "iconIdx": 224
    },
    {
      "icon": {
        "paths": [
          "M717.005 0h-410.010c-56.422 0-102.195 45.773-102.195 102.195v819.558c0 56.474 45.773 102.246 102.195 102.246h409.958c56.474 0 102.246-45.773 102.246-102.195v-819.61c0-56.422-45.773-102.195-102.195-102.195zM512 972.8c-35.328 0-64-22.886-64-51.2s28.672-51.2 64-51.2 64 22.886 64 51.2-28.672 51.2-64 51.2zM716.8 819.2h-409.6v-716.8h409.6v716.8z"
        ],
        "attrs": [],
        "isMulticolor": false,
        "isMulticolor2": false,
        "tags": [
          "mobile"
        ],
        "grid": 20
      },
      "attrs": [],
      "properties": {
        "id": 229,
        "order": 73,
        "prevSize": 20,
        "name": "mobile"
      },
      "setIdx": 2,
      "setId": 2,
      "iconIdx": 228
    },
    {
      "icon": {
        "paths": [
          "M574.925 574.925c-81.050 80.998-174.95 158.515-212.070 121.395-53.094-53.094-85.862-99.379-203.008-5.222-117.094 94.106-27.136 156.877 24.32 208.282 59.392 59.392 280.781 3.174 499.61-215.603 218.778-218.829 274.842-440.218 215.398-499.61-51.456-51.507-113.92-141.414-208.026-24.32-94.157 117.094-47.923 149.862 5.274 203.008 36.966 37.12-40.499 131.021-121.498 212.070z"
        ],
        "attrs": [],
        "isMulticolor": false,
        "isMulticolor2": false,
        "tags": [
          "phone"
        ],
        "grid": 20
      },
      "attrs": [],
      "properties": {
        "id": 245,
        "order": 68,
        "prevSize": 20,
        "name": "phone"
      },
      "setIdx": 2,
      "setId": 2,
      "iconIdx": 244
    },
    {
      "icon": {
        "paths": [
          "M621.312 476.365c-130.97-96.205-343.040 59.904-390.758 270.541-36.762 162.304-207.002 155.648-204.595 177.357 2.355 21.709 382.618 56.474 519.987-57.498 128.307-106.496 218.982-284.877 75.366-390.4zM734.106 77.21l-172.186 263.987c56.422 9.165 186.112 96.512 210.995 159.181l225.075-217.395c-26.931-76.954-176.026-196.813-263.885-205.773z"
        ],
        "attrs": [],
        "isMulticolor": false,
        "isMulticolor2": false,
        "tags": [
          "round-brush"
        ],
        "grid": 20
      },
      "attrs": [],
      "properties": {
        "id": 265,
        "order": 72,
        "prevSize": 20,
        "name": "round-brush"
      },
      "setIdx": 2,
      "setId": 2,
      "iconIdx": 264
    },
    {
      "icon": {
        "paths": [
          "M768 688.23c-32.41 0-61.645 12.595-83.814 32.87l-304.026-177.306c2.355-9.626 3.84-19.661 3.84-29.901s-1.485-20.224-3.84-29.85l300.8-175.565c22.835 21.35 53.35 34.56 87.040 34.56 70.605 0 128-57.395 128-128s-57.395-128-128-128-128 57.395-128 128c0 10.24 1.485 20.275 3.84 29.85l-300.8 175.565c-22.835-21.299-53.35-34.56-87.040-34.56-70.605 0-128 57.395-128 128s57.395 128 128 128c33.69 0 64.205-13.21 87.040-34.56l304.026 177.306c-2.15 8.96-3.43 18.33-3.43 27.955 0 68.71 55.654 124.365 124.365 124.365s124.365-55.706 124.365-124.365-55.654-124.365-124.365-124.365z"
        ],
        "attrs": [],
        "isMulticolor": false,
        "isMulticolor2": false,
        "tags": [
          "share"
        ],
        "grid": 20
      },
      "attrs": [],
      "properties": {
        "id": 270,
        "order": 69,
        "prevSize": 20,
        "name": "share"
      },
      "setIdx": 2,
      "setId": 2,
      "iconIdx": 269
    },
    {
      "icon": {
        "paths": [
          "M377.651 345.344c-22.886 14.080 61.286 217.19 81.818 250.266 17.92 29.133 55.962 37.99 84.89 20.173 29.082-18.022 38.144-56.013 20.224-84.992-20.326-33.178-164.096-199.578-186.931-185.446zM360.499 122.982c47.514-16.538 98.406-25.702 151.501-25.702s103.987 9.165 151.501 25.702c16.845 5.837 39.168-5.888 29.286-31.283-7.219-18.432-14.182-36.454-16.998-43.776-6.707-17.357-30.72-31.693-41.165-34.048-39.526-8.909-80.486-13.875-122.624-13.875s-83.098 4.966-122.675 13.875c-10.445 2.355-34.406 16.691-41.114 34.048-2.816 7.322-9.83 25.344-16.998 43.776-9.882 25.395 12.442 37.171 29.286 31.283zM977.818 163.123c-9.83-11.776-20.275-23.296-31.386-34.406-11.059-11.11-22.579-21.504-34.304-31.386-7.834-6.605-30.874-11.981-45.466 2.611-14.541 14.592-84.378 84.326-84.378 84.326 20.582 14.746 40.602 30.976 59.136 49.459s34.662 38.502 49.459 59.136c0 0 69.786-69.734 84.326-84.326 14.643-14.643 9.267-37.632 2.611-45.414zM512 148.48c-229.12 0-414.771 185.651-414.771 414.72 0 229.12 185.651 414.771 414.771 414.771 229.018 0 414.72-185.651 414.72-414.771 0-229.018-185.702-414.72-414.72-414.72zM512 875.571c-172.442 0-312.32-139.827-312.32-312.32s139.827-312.32 312.32-312.32c172.493 0 312.371 139.827 312.371 312.32 0 172.442-139.878 312.32-312.371 312.32z"
        ],
        "attrs": [],
        "isMulticolor": false,
        "isMulticolor2": false,
        "tags": [
          "stopwatch"
        ],
        "grid": 20
      },
      "attrs": [],
      "properties": {
        "id": 287,
        "order": 70,
        "prevSize": 20,
        "name": "stopwatch"
      },
      "setIdx": 2,
      "setId": 2,
      "iconIdx": 286
    },
    {
      "icon": {
        "paths": [
          "M819.2 51.2h-614.4c-28.314 0-51.2 22.886-51.2 51.2v819.2c0 28.262 22.886 51.2 51.2 51.2h614.4c28.314 0 51.2-22.938 51.2-51.2v-819.2c0-28.262-22.886-51.2-51.2-51.2zM768 870.4h-512v-716.8h512v716.8zM665.6 256h-307.2v102.4h307.2v-102.4zM665.6 665.6h-307.2v102.4h307.2v-102.4zM665.6 460.8h-307.2v102.4h307.2v-102.4z"
        ],
        "attrs": [],
        "isMulticolor": false,
        "isMulticolor2": false,
        "tags": [
          "text-document"
        ],
        "grid": 20
      },
      "attrs": [],
      "properties": {
        "id": 295,
        "order": 64,
        "prevSize": 20,
        "name": "text-document"
      },
      "setIdx": 2,
      "setId": 2,
      "iconIdx": 294
    },
    {
      "icon": {
        "paths": [
          "M395.52 109.875c-52.019 38.707-65.997 99.994-63.437 132.608 3.277 39.885 11.366 91.802 11.366 91.802s-16.026 8.704-16.026 43.725c5.581 87.91 34.97 49.971 41.011 88.525 14.541 92.877 47.77 76.339 47.77 127.027 0 84.429-34.816 123.904-143.514 170.701-109.056 47.002-221.491 106.138-221.491 208.538v51.2h921.6v-51.2c0-102.4-112.486-161.536-221.594-208.486-108.698-46.797-143.411-86.221-143.411-170.701 0-50.688 33.126-34.15 47.718-127.027 6.093-38.554 35.43-0.614 41.114-88.525 0-35.021-16.077-43.725-16.077-43.725s8.090-51.917 11.315-91.802c3.328-41.83-20.378-131.123-117.76-158.515-17.050-17.408-28.57-45.107 23.859-72.909-114.688-5.376-141.363 54.63-202.445 98.765z"
        ],
        "attrs": [],
        "isMulticolor": false,
        "isMulticolor2": false,
        "tags": [
          "user"
        ],
        "grid": 20
      },
      "attrs": [],
      "properties": {
        "id": 311,
        "order": 60,
        "prevSize": 20,
        "name": "user"
      },
      "setIdx": 2,
      "setId": 2,
      "iconIdx": 310
    },
    {
      "icon": {
        "paths": [
          "M818.637 979.405c0-114.995-111.974-173.517-221.030-220.518-108.698-46.797-143.411-86.221-143.411-170.701 0-50.637 33.178-34.15 47.718-127.027 6.144-38.502 35.43-0.614 41.062-88.525 0-35.021-16.026-43.725-16.026-43.725s8.141-51.866 11.315-91.802c3.277-41.83-20.378-131.072-117.811-158.464-16.998-17.459-28.518-45.158 23.91-72.909-114.688-5.325-141.363 54.682-202.445 98.816-51.968 38.707-65.997 99.994-63.488 132.608 3.328 39.936 11.418 91.802 11.418 91.802s-16.077 8.704-16.077 43.725c5.632 87.962 35.021 50.022 41.114 88.525 14.541 92.877 47.77 76.39 47.77 127.027 0 84.48-10.854 113.152-119.603 159.949-109.107 46.95-143.053 122.214-142.49 231.219 0.154 32.614-0.563 44.595-0.563 44.595h819.2c0 0-0.563-11.981-0.563-44.595zM948.634 684.288c-58.112-23.398-82.176-51.302-82.176-105.779 0-32.819 21.402-22.118 30.822-82.074 3.942-24.781 22.886-0.41 26.522-57.088 0-22.579-10.342-28.211-10.342-28.211s5.274-33.587 7.322-59.341c2.56-32.102-18.637-115.046-116.122-115.046-97.434 0-118.682 82.944-116.173 115.046 2.15 25.702 7.373 59.341 7.373 59.341s-10.342 5.581-10.342 28.211c3.635 56.678 22.579 32.307 26.522 57.088 9.421 60.006 30.822 49.306 30.822 82.074 0 54.477-22.426 79.974-92.621 110.182-3.533 1.485-6.144 3.482-9.37 5.222 83.968 36.454 216.371 99.379 247.706 227.686h135.424c0 0 0-97.587 0-118.682 0-51.2-13.978-93.901-75.366-118.63z"
        ],
        "attrs": [],
        "isMulticolor": false,
        "isMulticolor2": false,
        "tags": [
          "users"
        ],
        "grid": 20
      },
      "attrs": [],
      "properties": {
        "id": 312,
        "order": 61,
        "prevSize": 20,
        "name": "users"
      },
      "setIdx": 2,
      "setId": 2,
      "iconIdx": 311
    },
    {
      "icon": {
        "paths": [
          "M665.6 512c0 84.838-68.762 153.6-153.6 153.6s-153.6-68.762-153.6-153.6c0-8.755 0.922-17.306 2.509-25.6h-53.709v204.646c0 14.234 11.52 25.754 25.754 25.754h358.144c14.182 0 25.702-11.52 25.702-25.754v-204.646h-53.709c1.587 8.294 2.509 16.845 2.509 25.6zM512 614.4c56.525 0 102.4-45.875 102.4-102.4s-45.875-102.4-102.4-102.4-102.4 45.875-102.4 102.4 45.875 102.4 102.4 102.4zM634.88 404.48h61.389c8.499 0 15.411-6.912 15.411-15.36v-61.389c0-8.499-6.912-15.411-15.411-15.411h-61.389c-8.499 0-15.411 6.912-15.411 15.411v61.389c0.051 8.448 6.963 15.36 15.411 15.36zM512 20.48c-271.462 0-491.52 220.058-491.52 491.52s220.058 491.52 491.52 491.52c271.462 0 491.52-220.058 491.52-491.52s-220.058-491.52-491.52-491.52zM768 711.117c0 31.283-25.6 56.883-56.883 56.883h-398.234c-31.283 0-56.883-25.6-56.883-56.883v-398.234c0-31.283 25.6-56.883 56.883-56.883h398.234c31.283 0 56.883 25.6 56.883 56.883v398.234z"
        ],
        "attrs": [],
        "isMulticolor": false,
        "isMulticolor2": false,
        "tags": [
          "instagram-with-circle"
        ],
        "grid": 20
      },
      "attrs": [],
      "properties": {
        "id": 367,
        "order": 34,
        "prevSize": 20,
        "name": "instagram-with-circle"
      },
      "setIdx": 2,
      "setId": 2,
      "iconIdx": 366
    },
    {
      "icon": {
        "paths": [
          "M512 20.48c-271.462 0-491.52 220.058-491.52 491.52s220.058 491.52 491.52 491.52 491.52-220.058 491.52-491.52-220.058-491.52-491.52-491.52zM391.68 715.725h-99.533v-320.307h99.533v320.307zM341.299 356.096c-31.437 0-51.763-22.272-51.763-49.818 0-28.109 20.941-49.715 53.043-49.715s51.763 21.606 52.378 49.715c0 27.546-20.275 49.818-53.658 49.818zM755.2 715.725h-99.533v-177.51c0-41.318-14.438-69.376-50.432-69.376-27.494 0-43.827 18.995-51.046 37.274-2.662 6.502-3.328 15.718-3.328 24.883v184.678h-99.584v-218.112c0-39.987-1.28-73.421-2.611-102.195h86.477l4.557 44.493h1.997c13.107-20.89 45.21-51.712 98.918-51.712 65.485 0 114.586 43.878 114.586 138.189v189.389z"
        ],
        "attrs": [],
        "isMulticolor": false,
        "isMulticolor2": false,
        "tags": [
          "linkedin-with-circle"
        ],
        "grid": 20
      },
      "attrs": [],
      "properties": {
        "id": 371,
        "order": 35,
        "prevSize": 20,
        "name": "linkedin-with-circle"
      },
      "setIdx": 2,
      "setId": 2,
      "iconIdx": 370
    },
    {
      "icon": {
        "paths": [
          "M384 640l128-64 448-448-64-64-448 448-64 128zM289.3 867.098c-31.632-66.728-65.666-100.762-132.396-132.394l99.096-272.792 128-77.912 384-384h-192l-384 384-192 640 640-192 384-384v-192l-384 384-77.912 128z"
        ],
        "tags": [
          "pencil",
          "write",
          "edit"
        ],
        "defaultCode": 59654,
        "grid": 16,
        "attrs": []
      },
      "attrs": [],
      "properties": {
        "ligatures": "pencil2, write2",
        "name": "pencil2",
        "order": 37,
        "id": 7,
        "prevSize": 20
      },
      "setIdx": 3,
      "setId": 1,
      "iconIdx": 6
    },
    {
      "icon": {
        "paths": [
          "M0 1024c128-384 463-1024 1024-1024-263 211-384 704-576 704s-192 0-192 0l-192 320h-64z"
        ],
        "tags": [
          "quill",
          "feather",
          "write",
          "edit"
        ],
        "defaultCode": 59655,
        "grid": 16,
        "attrs": []
      },
      "attrs": [],
      "properties": {
        "ligatures": "quill, feather",
        "name": "quill",
        "order": 39,
        "id": 8,
        "prevSize": 20
      },
      "setIdx": 3,
      "setId": 1,
      "iconIdx": 7
    },
    {
      "icon": {
        "paths": [
          "M1018.17 291.89l-286.058-286.058c-9.334-9.334-21.644-7.234-27.356 4.666l-38.354 79.904 267.198 267.198 79.904-38.354c11.9-5.712 14-18.022 4.666-27.356z",
          "M615.384 135.384l-263.384 21.95c-17.5 2.166-32.080 5.898-37.090 28.752-0.006 0.024-0.012 0.042-0.018 0.066-71.422 343.070-314.892 677.848-314.892 677.848l57.374 57.374 271.986-271.99c-5.996-12.53-9.36-26.564-9.36-41.384 0-53.020 42.98-96 96-96s96 42.98 96 96-42.98 96-96 96c-14.82 0-28.852-3.364-41.384-9.36l-271.988 271.986 57.372 57.374c0 0 334.778-243.47 677.848-314.892 0.024-0.006 0.042-0.012 0.066-0.018 22.854-5.010 26.586-19.59 28.752-37.090l21.95-263.384-273.232-273.232z"
        ],
        "tags": [
          "pen",
          "write",
          "edit"
        ],
        "defaultCode": 59656,
        "grid": 16,
        "attrs": []
      },
      "attrs": [],
      "properties": {
        "ligatures": "pen, write3",
        "name": "pen",
        "order": 38,
        "id": 9,
        "prevSize": 20
      },
      "setIdx": 3,
      "setId": 1,
      "iconIdx": 8
    },
    {
      "icon": {
        "paths": [
          "M621.254 877.254l320-320c24.994-24.992 24.994-65.516 0-90.51l-320-320c-24.994-24.992-65.516-24.992-90.51 0-24.994 24.994-24.994 65.516 0 90.51l210.746 210.746h-613.49c-35.346 0-64 28.654-64 64s28.654 64 64 64h613.49l-210.746 210.746c-12.496 12.496-18.744 28.876-18.744 45.254s6.248 32.758 18.744 45.254c24.994 24.994 65.516 24.994 90.51 0z"
        ],
        "tags": [
          "arrow-right",
          "right",
          "next"
        ],
        "defaultCode": 59964,
        "grid": 16,
        "attrs": []
      },
      "attrs": [],
      "properties": {
        "ligatures": "arrow-right2, right4",
        "name": "arrow-right2",
        "order": 36,
        "id": 317,
        "prevSize": 20
      },
      "setIdx": 3,
      "setId": 1,
      "iconIdx": 316
    },
    {
      "icon": {
        "paths": [
          "M512 0c-282.77 0-512 229.23-512 512s229.23 512 512 512 512-229.23 512-512-229.23-512-512-512zM256 256h512c9.138 0 18.004 1.962 26.144 5.662l-282.144 329.168-282.144-329.17c8.14-3.696 17.006-5.66 26.144-5.66zM192 704v-384c0-1.34 0.056-2.672 0.14-4l187.664 218.942-185.598 185.598c-1.444-5.336-2.206-10.886-2.206-16.54zM768 768h-512c-5.654 0-11.202-0.762-16.54-2.208l182.118-182.118 90.422 105.498 90.424-105.494 182.116 182.12c-5.34 1.44-10.886 2.202-16.54 2.202zM832 704c0 5.654-0.762 11.2-2.206 16.54l-185.6-185.598 187.666-218.942c0.084 1.328 0.14 2.66 0.14 4v384z"
        ],
        "tags": [
          "mail",
          "contact",
          "support",
          "newsletter",
          "letter",
          "email",
          "envelop",
          "social"
        ],
        "defaultCode": 60038,
        "grid": 16,
        "attrs": []
      },
      "attrs": [],
      "properties": {
        "ligatures": "mail5, contact5",
        "name": "mail4",
        "order": 30,
        "id": 391,
        "prevSize": 20
      },
      "setIdx": 3,
      "setId": 1,
      "iconIdx": 390
    }
  ],
  "height": 1024,
  "preferences": {
    "showGlyphs": true,
    "showQuickUse": true,
    "showQuickUse2": true,
    "showSVGs": true,
    "fontPref": {
      "prefix": "icon-",
      "metadata": {
        "fontFamily": "icomoon"
      },
      "metrics": {
        "emSize": 1024,
        "baseline": 6.25,
        "whitespace": 50
      },
      "embed": false
    },
    "imagePref": {
      "prefix": "icon-",
      "png": false,
      "useClassSelector": true,
      "color": 0,
      "bgColor": 16777215,
      "classSelector": ".icon",
      "name": "icomoon",
      "height": 32,
      "columns": 16,
      "margin": 16
    },
    "historySize": 50,
    "showCodes": true,
    "gridSize": 16
  }
}